{"qq":1622977224,"code_name":"U-19","title":"","register":{"registration_group_number":1062012716,"registration_time":"2020-08-19","registered_nickname":"\u671d\u706c\u65e5","register_group_business_card":"\u67da\u5b50"},"resources":{"gold":1000,"foodstuff":3000},"game":{"last_game_time":"2020-08-23","last_game_time_group":1062012716,"times_of_play":1},"battle":{"combat_effectiveness":0,"frequency":0,"victory":0,"fail":0,"number_of_battles_of_the_day":0,"last_battle_time":"2017-10-01"},"knapsack":[],"entourage":{"number":0,"follower_information":[]}}